{"settings.enable":false,"planets":"{\"1:145:4-moon\":{\"coordinate\":\"1:145:4\",\"type\":\"moon\",\"delay\":300,\"updateAt\":1723749649246,\"left\":-50398},\"1:145:4-planet\":{\"delay\":670,\"coordinate\":\"1:145:4\",\"type\":\"planet\",\"updateAt\":1723799428672,\"left\":-249},\"1:145:8-moon\":{\"coordinate\":\"1:145:8\",\"type\":\"moon\",\"delay\":300,\"updateAt\":1723650007428,\"left\":-150040},\"1:145:8-planet\":{\"delay\":633,\"coordinate\":\"1:145:8\",\"type\":\"planet\",\"updateAt\":1723799492731,\"left\":-222},\"1:145:7-planet\":{\"delay\":614,\"coordinate\":\"1:145:7\",\"type\":\"planet\",\"updateAt\":1723799491147,\"left\":-242},\"1:145:9-planet\":{\"delay\":713,\"coordinate\":\"1:145:9\",\"type\":\"planet\",\"updateAt\":1723799495348,\"left\":-139},\"1:146:7-planet\":{\"delay\":776,\"coordinate\":\"1:146:7\",\"type\":\"planet\",\"updateAt\":1723799496465,\"left\":-75},\"1:144:9-planet\":{\"delay\":711,\"coordinate\":\"1:144:9\",\"type\":\"planet\",\"updateAt\":1723799497984,\"left\":-139},\"1:151:7-planet\":{\"delay\":731,\"coordinate\":\"1:151:7\",\"type\":\"planet\",\"updateAt\":1723799498866,\"left\":-118},\"2:241:7-planet\":{\"delay\":665,\"coordinate\":\"2:241:7\",\"type\":\"planet\",\"updateAt\":1723799500747,\"left\":-182},\"2:241:9-planet\":{\"delay\":757,\"coordinate\":\"2:241:9\",\"type\":\"planet\",\"updateAt\":1723793374264,\"left\":-6216},\"3:246:7-planet\":{\"delay\":717,\"coordinate\":\"3:246:7\",\"type\":\"planet\",\"updateAt\":1723799503035,\"left\":-128},\"3:242:7-planet\":{\"delay\":603,\"coordinate\":\"3:242:7\",\"type\":\"planet\",\"updateAt\":1723800020984,\"left\":275},\"3:226:7-planet\":{\"delay\":774,\"coordinate\":\"3:226:7\",\"type\":\"planet\",\"updateAt\":1723793412821,\"left\":-6161},\"3:189:9-planet\":{\"delay\":738,\"coordinate\":\"3:189:9\",\"type\":\"planet\",\"updateAt\":1723793419301,\"left\":-6190},\"1:236:9-moon\":{\"coordinate\":\"1:236:9\",\"type\":\"moon\",\"delay\":300,\"updateAt\":1723650008996,\"left\":-150039},\"1:236:9-planet\":{\"delay\":764,\"coordinate\":\"1:236:9\",\"type\":\"planet\",\"updateAt\":1723799493853,\"left\":-90},\"1:338:7-planet\":{\"delay\":687,\"coordinate\":\"1:338:7\",\"type\":\"planet\",\"updateAt\":1723793426188,\"left\":-6234},\"1:287:9-planet\":{\"delay\":642,\"coordinate\":\"1:287:9\",\"type\":\"planet\",\"updateAt\":1723800348111,\"left\":642},\"1:212:8-planet\":{\"delay\":732,\"coordinate\":\"1:212:8\",\"type\":\"planet\",\"updateAt\":1723793432145,\"left\":-6183},\"1:374:7-planet\":{\"delay\":653,\"coordinate\":\"1:374:7\",\"type\":\"planet\",\"updateAt\":1723793438046,\"left\":-6257},\"1:56:9-planet\":{\"delay\":725,\"coordinate\":\"1:56:9\",\"type\":\"planet\",\"updateAt\":1723793444198,\"left\":-6178},\"1:346:9-moon\":{\"coordinate\":\"1:346:9\",\"type\":\"moon\",\"delay\":120,\"updateAt\":1723619100268,\"left\":-181127},\"1:346:9-planet\":{\"delay\":120,\"coordinate\":\"1:346:9\",\"type\":\"planet\",\"updateAt\":1723793449444,\"left\":-6778},\"1:114:7-planet\":{\"delay\":767,\"coordinate\":\"1:114:7\",\"type\":\"planet\",\"updateAt\":1723793455196,\"left\":-6125},\"1:145:15-planet\":{\"delay\":679,\"coordinate\":\"1:145:15\",\"type\":\"planet\",\"updateAt\":1723793460541,\"left\":-6208},\"1:287:9-moon\":{\"coordinate\":\"1:287:9\",\"type\":\"moon\",\"delay\":300,\"updateAt\":1723770495348,\"left\":-29552},\"1:37:9-planet\":{\"delay\":657,\"coordinate\":\"1:37:9\",\"type\":\"planet\",\"updateAt\":1723793467508,\"left\":-6223},\"1:37:9-moon\":{\"coordinate\":\"1:37:9\",\"type\":\"moon\",\"delay\":300,\"updateAt\":1723650003850,\"left\":-150044},\"1:144:15-planet\":{\"delay\":729,\"coordinate\":\"1:144:15\",\"type\":\"planet\",\"updateAt\":1723793481066,\"left\":-6138},\"4:119:7-planet\":{\"delay\":701,\"coordinate\":\"4:119:7\",\"type\":\"planet\",\"updateAt\":1723793509064,\"left\":-6138},\"1:287:15-planet\":{\"delay\":730,\"coordinate\":\"1:287:15\",\"type\":\"planet\",\"updateAt\":1723793488582,\"left\":-6129},\"1:236:15-planet\":{\"delay\":756,\"coordinate\":\"1:236:15\",\"type\":\"planet\",\"updateAt\":1723793500695,\"left\":-6091}}"}